passlib/__init__.py
passlib/_logging.py
passlib/_protocols.py
passlib/apache.py
passlib/apps.py
passlib/context.py
passlib/exc.py
passlib/hash.py
passlib/hosts.py
passlib/ifc.py
passlib/pwd.py
passlib/registry.py
passlib/totp.py
passlib/_data/wordsets/bip39.txt
passlib/_data/wordsets/eff_long.txt
passlib/_data/wordsets/eff_prefixed.txt
passlib/_data/wordsets/eff_short.txt
passlib/crypto/__init__.py
passlib/crypto/_md4.py
passlib/crypto/des.py
passlib/crypto/digest.py
passlib/crypto/_blowfish/__init__.py
passlib/crypto/_blowfish/_gen_files.py
passlib/crypto/_blowfish/base.py
passlib/crypto/_blowfish/unrolled.py
passlib/crypto/scrypt/__init__.py
passlib/crypto/scrypt/_builtin.py
passlib/crypto/scrypt/_gen_files.py
passlib/crypto/scrypt/_salsa.py
passlib/ext/__init__.py
passlib/ext/django/__init__.py
passlib/ext/django/models.py
passlib/ext/django/utils.py
passlib/handlers/__init__.py
passlib/handlers/argon2.py
passlib/handlers/bcrypt.py
passlib/handlers/cisco.py
passlib/handlers/des_crypt.py
passlib/handlers/digests.py
passlib/handlers/django.py
passlib/handlers/fshp.py
passlib/handlers/ldap_digests.py
passlib/handlers/md5_crypt.py
passlib/handlers/misc.py
passlib/handlers/mssql.py
passlib/handlers/mysql.py
passlib/handlers/oracle.py
passlib/handlers/pbkdf2.py
passlib/handlers/phpass.py
passlib/handlers/postgres.py
passlib/handlers/roundup.py
passlib/handlers/scram.py
passlib/handlers/scrypt.py
passlib/handlers/sha1_crypt.py
passlib/handlers/sha2_crypt.py
passlib/handlers/sun_md5_crypt.py
passlib/handlers/windows.py
passlib/utils/__init__.py
passlib/utils/binary.py
passlib/utils/decor.py
passlib/utils/des.py
passlib/utils/handlers.py
passlib/utils/md4.py
passlib/utils/pbkdf2.py
passlib/utils/compat/__init__.py
libpass-1.9.2.dist-info/METADATA
libpass-1.9.2.dist-info/WHEEL
libpass-1.9.2.dist-info/licenses/LICENSE
libpass-1.9.2.dist-info/RECORD
