Metadata-Version: 2.4
Name: libpass
Version: 1.9.2
Summary: Fork of passlib, a comprehensive password hashing framework supporting over 30 schemes
Project-URL: Homepage, https://github.com/notypecheck/passlib
Project-URL: Repository, https://github.com/notypecheck/passlib
Project-URL: Docs, https://passlib.readthedocs.io
Project-URL: Issues, https://github.com/notypecheck/passlib/issues
Project-URL: Changelog, https://github.com/notypecheck/passlib/blob/main/CHANGELOG.md
Author-email: Eli Collins <elic@assurancetechnologies.com>
Maintainer-email: Doctor <notypecheck@gmail.com>
License: BSD
License-File: LICENSE
Keywords: 2fa,apache,argon2,bcrypt,crypt,hash,htdigest,htpasswd,md5-crypt,passlib,password,pbkdf2,scrypt,secret,security,sha256-crypt,sha512-crypt,totp
Classifier: Development Status :: 3 - Alpha
Classifier: Intended Audience :: Developers
Classifier: License :: OSI Approved :: BSD License
Classifier: Natural Language :: English
Classifier: Operating System :: OS Independent
Classifier: Programming Language :: Python :: 3
Classifier: Programming Language :: Python :: 3.9
Classifier: Programming Language :: Python :: 3.10
Classifier: Programming Language :: Python :: 3.11
Classifier: Programming Language :: Python :: 3.12
Classifier: Programming Language :: Python :: 3.13
Classifier: Programming Language :: Python :: Implementation :: CPython
Classifier: Topic :: Security :: Cryptography
Classifier: Topic :: Software Development :: Libraries
Requires-Python: >=3.9
Provides-Extra: argon2
Requires-Dist: argon2-cffi>=18.2.0; extra == 'argon2'
Provides-Extra: bcrypt
Requires-Dist: bcrypt<5.0.0; extra == 'bcrypt'
Provides-Extra: totp
Requires-Dist: cryptography>=43.0.1; extra == 'totp'
